{
    "summary": "This code imports a BaiduSpider class and uses it to search for an image related to the keyword \"\u7edd\u5bf9\u9886\u57df\". It then prints the result and checks if the 'title', 'url', and 'host' information is available.",
    "details": [
        {
            "comment": "This code imports a BaiduSpider class and uses it to search for an image related to the keyword \"\u7edd\u5bf9\u9886\u57df\". It then prints the result and checks if the 'title', 'url', and 'host' information is available.",
            "location": "\"/media/root/Toshiba XG3/works/pyjom_doc/src/tests/search_engine_suggestion_based_qa_bot/search_image_with_keywords.py\":0-12",
            "content": "# not sure if it relates.\nfrom baiduspider import BaiduSpider\nspider=BaiduSpider()\nfrom pprint import pprint\nquery = \"\u7edd\u5bf9\u9886\u57df\"\nresult = spider.search_pic(query, pn= 1) # are we fucked?\n# yeah we have result.\nprint(result)\nresult.plain\nbreakpoint()\n# 'title', 'url', 'host'\n# can we search for gif?"
        }
    ]
}