{
    "summary": "This code extracts content from a dictionary representing an XML message, assigns it to a variable, and prints it, possibly for debugging or validation purposes.",
    "details": [
        {
            "comment": "This code contains a dictionary named \"contentDictString\" that represents an XML message with information about a video recommendation from Bilibili, including the template ID, URL, service ID, action, action data, i_actionData, brief, layout, picture, title, summary, source URL, icon, name, appid, and more.",
            "location": "\"/media/root/Toshiba XG3/works/pyjom_doc/src/tests/bilibili_video_recommendation_server/xml_and_json_qq_send/new_xml.py\":0-0",
            "content": "contentDictString = {\"Content\":\"\\u003c?xml version='1.0' encoding='UTF-8' standalone='yes'?\\u003e\\u003cmsg templateID=\\\"123\\\" url=\\\"https://b23.tv/uHML5mi?share_medium=android\\u0026amp;share_source=qq\\u0026amp;bbid=XY1BB721B1F97348DBDE4297FE1B4ABE26BAA\\u0026amp;ts=1666023406285\\\" serviceID=\\\"1\\\" action=\\\"web\\\" actionData=\\\"\\\" a_actionData=\\\"\\\" i_actionData=\\\"\\\" brief=\\\"[QQ\u5c0f\u7a0b\u5e8f]\u54d4\u54e9\u54d4\u54e9\\\" flag=\\\"0\\\"\\u003e\\u003citem layout=\\\"2\\\"\\u003e\\u003cpicture cover=\\\"http://pubminishare-30161.picsz.qpic.cn/c099bdd6-9e61-43d9-b82f-c9d5354ace68\\\"/\\u003e\\u003ctitle\\u003e\u54d4\u54e9\u54d4\u54e9\\u003c/title\\u003e\\u003csummary\\u003e\u3010AI\u52a8\u753b\u3011\u59ae\u9732PV\u52a8\u753b \u98ce\u8f6c\u6362\u3010NovelAI\u3011\\u003c/summary\\u003e\\u003c/item\\u003e\\u003csource url=\\\"https://b23.tv/uHML5mi?share_medium=android\\u0026amp;share_source=qq\\u0026amp;bbid=XY1BB721B1F97348DBDE4297FE1B4ABE26BAA\\u0026amp;ts=1666023406285\\\" icon=\\\"http://miniapp.gtimg.cn/public/appicon/432b76be3a548fc128acaa6c1ec90131_200.jpg\\\" name=\\\"\u54d4\u54e9\u54d4\u54e9\\\" appid=\\\"0\\\" action=\\\"web\\\" actionData=\\\"\\\" a_actionData=\\\"tencent0://\\\" i_actionData=\\\"\\\"/\\u003e\\u003c/msg\\u003e\"}"
        },
        {
            "comment": "Content from the string is being assigned to the dictionary variable 'contentDict'. The 'Content' key in this dictionary is then extracted and stored in the variable 'content', which is finally printed. This code appears to print the content of a certain element in a file, potentially for debugging or validation purposes.",
            "location": "\"/media/root/Toshiba XG3/works/pyjom_doc/src/tests/bilibili_video_recommendation_server/xml_and_json_qq_send/new_xml.py\":2-5",
            "content": "contentDict = contentDictString\ncontent = contentDict['Content']\nprint(content)"
        }
    ]
}