{
    "summary": "This code is using the mitmproxy tool to read a log file named \"qq.log\" for analysis or debugging purposes.",
    "details": [
        {
            "comment": "This code is using the mitmproxy tool to read a log file named \"qq.log\" for analysis or debugging purposes.",
            "location": "\"/media/root/Toshiba XG3/works/pyjom_doc/src/tests/bilibili_video_recommendation_server/xml_and_json_qq_send/view_qq.sh\":0-0",
            "content": "mitmproxy -r qq.log"
        }
    ]
}